phoss/__init__.py
phoss/base_schedulers.py
phoss/common.py
phoss/experiment_analysis.py
phoss/experiment_group.py
phoss/experiment_runner.py
phoss/experiment_visualizer.py
phoss/landscaper.py
phoss/ray_runner.py
phoss/schedulers.py
phoss/trainables.py
phoss/visualization_example.py
phoss-1.0.0.dist-info/LICENSE
phoss-1.0.0.dist-info/METADATA
phoss-1.0.0.dist-info/WHEEL
phoss-1.0.0.dist-info/top_level.txt
phoss-1.0.0.dist-info/RECORD
