Metadata-Version: 2.1
Name: phoss
Version: 1.0.0
Summary: A hyperparameter search simulation platform for distributed testing of scheduling algorithms.
Author-email: Jeremy Hsu <jeremyhsu1@gmail.com>, Aakash Mishra <aakamishra1@gmail.com>, Frank D'Agostino <frankdag20@gmail.com>
License: Apache License
Project-URL: Source, https://github.com/aakamishra/phoss
Classifier: Development Status :: 3 - Alpha
Classifier: License :: OSI Approved :: Apache Software License
Classifier: Programming Language :: Python :: 3.9
Classifier: Programming Language :: Python :: 3.10
Classifier: Topic :: Scientific/Engineering :: Artificial Intelligence
Classifier: Topic :: Software Development :: Libraries :: Python Modules
Classifier: Topic :: System :: Distributed Computing
Requires-Python: >=3.9
License-File: LICENSE
Requires-Dist: matplotlib (>=3.5.2)
Requires-Dist: numpy (>=1.23.1)
Requires-Dist: pandas (>=1.4.4)
Requires-Dist: ray[air]
Requires-Dist: ray[tune]
Requires-Dist: scikit-learn (>=1.1.2)
Requires-Dist: scipy (>=1.9.1)
Requires-Dist: seaborn (>=0.11.2)
